vars_localize/__init__.py
vars_localize/__main__.py
vars_localize/assets/__init__.py
vars_localize/assets/images/arrow_left.png
vars_localize/assets/images/arrow_right.png
vars_localize/ui/AppWindow.py
vars_localize/ui/BoundingBox.py
vars_localize/ui/ConceptEntry.py
vars_localize/ui/ConceptSearchbar.py
vars_localize/ui/DisplayPanel.py
vars_localize/ui/EntryTree.py
vars_localize/ui/ImageView.py
vars_localize/ui/JSONTree.py
vars_localize/ui/LoginDialog.py
vars_localize/ui/Paginator.py
vars_localize/ui/PropertiesDialog.py
vars_localize/ui/PropertiesForm.py
vars_localize/ui/SearchPanel.py
vars_localize/ui/__init__.py
vars_localize/util/__init__.py
vars_localize/util/endpoints.py
vars_localize/util/m3.py
vars_localize/util/utils.py
vars_localize-0.1.0.dist-info/METADATA
vars_localize-0.1.0.dist-info/WHEEL
vars_localize-0.1.0.dist-info/entry_points.txt
vars_localize-0.1.0.dist-info/RECORD
