Metadata-Version: 2.3
Name: vars-localize
Version: 0.1.0
Summary: Tool for creating localization with VARS.
Author-email: Kevin Barnard <kbarnard@mbari.org>
Requires-Python: >=3.8
Requires-Dist: pyqt6>=6.7.1
Requires-Dist: qdarkstyle>=3.2.3
Requires-Dist: requests>=2.32.3
